{"I11": {"segments": []}, "I13": {"segments": [{"bitrate": 776386.0, "codec": "h264", "duration": 4, "fps": 24.0, "resolution": "512x288", "start": 0}, {"bitrate": 551419.0, "codec": "h264", "duration": 4, "fps": 24.0, "resolution": "512x288", "start": 4}, {"bitrate": 553067.0, "codec": "h264", "duration": 4, "fps": 24.0, "resolution": "512x288", "start": 8}, {"bitrate": 551938.0, "codec": "h264", "duration": 4, "fps": 24.0, "resolution": "512x288", "start": 12}, {"bitrate": 370051.0, "codec": "h264", "duration": 4, "fps": 24.0, "resolution": "384x216", "start": 16}, {"bitrate": 233285.0, "codec": "h264", "duration": 4, "fps": 24.0, "resolution": "320x180", "start": 20}, {"bitrate": 232581.0, "codec": "h264", "duration": 4, "fps": 24.0, "resolution": "320x180", "start": 24}]}, "I23": {"stalling": [[12, 0.20709012140813154], [16, 1.366354403554567], [20, 1.8027972543110682]]}, "IGen": {"device": "tv", "displaySize": "1920x1080", "viewingDistance": "100cm"}}