{"I11": {"segments": []}, "I13": {"segments": [{"bitrate": 1045.008, "codec": "h264", "duration": 4, "fps": 30.0, "resolution": "640x360", "start": 0}, {"bitrate": 1024.544, "codec": "h264", "duration": 4, "fps": 30.0, "resolution": "640x360", "start": 4}, {"bitrate": 452.558, "codec": "h264", "duration": 4, "fps": 30.0, "resolution": "640x360", "start": 8}, {"bitrate": 900.704, "codec": "h264", "duration": 4, "fps": 30.0, "resolution": "640x360", "start": 12}, {"bitrate": 1359.58, "codec": "h264", "duration": 4, "fps": 30.0, "resolution": "640x360", "start": 16}, {"bitrate": 1227.824, "codec": "h264", "duration": 4, "fps": 30.0, "resolution": "640x360", "start": 20}, {"bitrate": 1933.146, "codec": "h264", "duration": 4, "fps": 30.0, "resolution": "960x540", "start": 24}]}, "I23": {"stalling": []}, "IGen": {"device": "phone", "displaySize": "1920x1080", "viewingDistance": "20cm"}}