{"I11": {"segments": []}, "I13": {"segments": [{"bitrate": 4224612.0, "codec": "h264", "duration": 4, "fps": 24.0, "resolution": "1920x1080", "start": 0}, {"bitrate": 2954661.0, "codec": "h264", "duration": 4, "fps": 24.0, "resolution": "1280x720", "start": 4}, {"bitrate": 3009660.0, "codec": "h264", "duration": 4, "fps": 24.0, "resolution": "1280x720", "start": 8}, {"bitrate": 2947965.0, "codec": "h264", "duration": 4, "fps": 24.0, "resolution": "1280x720", "start": 12}, {"bitrate": 2955090.0, "codec": "h264", "duration": 4, "fps": 24.0, "resolution": "1280x720", "start": 16}, {"bitrate": 2312024.0, "codec": "h264", "duration": 4, "fps": 24.0, "resolution": "1280x720", "start": 20}, {"bitrate": 2308232.0, "codec": "h264", "duration": 4, "fps": 24.0, "resolution": "1280x720", "start": 24}]}, "I23": {"stalling": []}, "IGen": {"device": "tv", "displaySize": "1920x1080", "viewingDistance": "100cm"}}