{"I11": {"segments": []}, "I13": {"segments": [{"bitrate": 236.982, "codec": "h264", "duration": 4, "fps": 30.0, "resolution": "320x180", "start": 0}, {"bitrate": 598.856, "codec": "h264", "duration": 4, "fps": 30.0, "resolution": "512x288", "start": 4}, {"bitrate": 2572.82, "codec": "h264", "duration": 4, "fps": 30.0, "resolution": "1280x720", "start": 8}, {"bitrate": 5275.888, "codec": "h264", "duration": 4, "fps": 30.0, "resolution": "1920x1080", "start": 12}, {"bitrate": 2794.754, "codec": "h264", "duration": 4, "fps": 30.0, "resolution": "1280x720", "start": 16}, {"bitrate": 4615.866, "codec": "h264", "duration": 4, "fps": 30.0, "resolution": "1920x1080", "start": 20}, {"bitrate": 4966.524, "codec": "h264", "duration": 4, "fps": 30.0, "resolution": "1920x1080", "start": 24}]}, "I23": {"stalling": []}, "IGen": {"device": "phone", "displaySize": "1920x1080", "viewingDistance": "20cm"}}